{"name": "Becky", "rows": [{"time": "1993-09-13 06:00:00", "power": 1, "lat": 13.5, "lng": 130.5, "PRES": 1005.0, "WND": 12.0}, {"time": "1993-09-13 12:00:00", "power": 1, "lat": 13.8, "lng": 129.8, "PRES": 1005.0, "WND": 12.0}, {"time": "1993-09-13 18:00:00", "power": 1, "lat": 14.3, "lng": 129.0, "PRES": 1005.0, "WND": 12.0}, {"time": "1993-09-14 00:00:00", "power": 1, "lat": 15.0, "lng": 128.0, "PRES": 1002.0, "WND": 15.0}, {"time": "1993-09-14 06:00:00", "power": 1, "lat": 15.5, "lng": 127.2, "PRES": 1002.0, "WND": 15.0}, {"time": "1993-09-14 12:00:00", "power": 1, "lat": 16.2, "lng": 126.4, "PRES": 1002.0, "WND": 15.0}, {"time": "1993-09-14 18:00:00", "power": 1, "lat": 16.6, "lng": 125.8, "PRES": 1002.0, "WND": 15.0}, {"time": "1993-09-15 00:00:00", "power": 1, "lat": 17.3, "lng": 124.5, "PRES": 1000.0, "WND": 15.0}, {"time": "1993-09-15 06:00:00", "power": 1, "lat": 17.9, "lng": 123.6, "PRES": 1000.0, "WND": 15.0}, {"time": "1993-09-15 12:00:00", "power": 2, "lat": 18.7, "lng": 122.7, "PRES": 995.0, "WND": 20.0}, {"time": "1993-09-15 18:00:00", "power": 2, "lat": 18.9, "lng": 121.5, "PRES": 995.0, "WND": 20.0}, {"time": "1993-09-16 00:00:00", "power": 2, "lat": 18.8, "lng": 120.0, "PRES": 990.0, "WND": 20.0}, {"time": "1993-09-16 06:00:00", "power": 3, "lat": 19.3, "lng": 118.4, "PRES": 985.0, "WND": 25.0}, {"time": "1993-09-16 12:00:00", "power": 3, "lat": 20.0, "lng": 116.8, "PRES": 985.0, "WND": 25.0}, {"time": "1993-09-16 18:00:00", "power": 3, "lat": 20.8, "lng": 115.0, "PRES": 980.0, "WND": 30.0}, {"time": "1993-09-17 00:00:00", "power": 4, "lat": 21.7, "lng": 113.6, "PRES": 975.0, "WND": 35.0}, {"time": "1993-09-17 06:00:00", "power": 3, "lat": 22.3, "lng": 111.7, "PRES": 985.0, "WND": 25.0}, {"time": "1993-09-17 12:00:00", "power": 1, "lat": 22.5, "lng": 110.7, "PRES": 995.0, "WND": 15.0}, {"time": "1993-09-17 18:00:00", "power": 1, "lat": 22.5, "lng": 109.2, "PRES": 1002.0, "WND": 12.0}, {"time": "1993-09-18 00:00:00", "power": 1, "lat": 22.6, "lng": 108.0, "PRES": 1002.0, "WND": 12.0}, {"time": "1993-09-18 06:00:00", "power": 0, "lat": 22.4, "lng": 106.8, "PRES": 1004.0, "WND": 9.0}]}