{"name": "Keoni", "rows": [{"time": "1993-08-19 12:00:00", "power": 3, "lat": 20.1, "lng": 180.9, "PRES": 980.0, "WND": 30.0}, {"time": "1993-08-19 18:00:00", "power": 3, "lat": 20.3, "lng": 180.0, "PRES": 975.0, "WND": 30.0}, {"time": "1993-08-20 00:00:00", "power": 4, "lat": 20.7, "lng": 179.4, "PRES": 970.0, "WND": 35.0}, {"time": "1993-08-20 06:00:00", "power": 4, "lat": 21.3, "lng": 178.3, "PRES": 965.0, "WND": 40.0}, {"time": "1993-08-20 12:00:00", "power": 4, "lat": 21.9, "lng": 177.3, "PRES": 960.0, "WND": 40.0}, {"time": "1993-08-20 18:00:00", "power": 4, "lat": 22.6, "lng": 176.0, "PRES": 960.0, "WND": 40.0}, {"time": "1993-08-21 00:00:00", "power": 4, "lat": 23.1, "lng": 174.9, "PRES": 960.0, "WND": 40.0}, {"time": "1993-08-21 06:00:00", "power": 5, "lat": 23.7, "lng": 173.9, "PRES": 950.0, "WND": 45.0}, {"time": "1993-08-21 12:00:00", "power": 5, "lat": 24.5, "lng": 172.7, "PRES": 950.0, "WND": 45.0}, {"time": "1993-08-21 18:00:00", "power": 5, "lat": 25.3, "lng": 171.8, "PRES": 950.0, "WND": 45.0}, {"time": "1993-08-22 00:00:00", "power": 5, "lat": 26.1, "lng": 171.2, "PRES": 950.0, "WND": 45.0}, {"time": "1993-08-22 06:00:00", "power": 4, "lat": 26.8, "lng": 170.6, "PRES": 960.0, "WND": 40.0}, {"time": "1993-08-22 12:00:00", "power": 4, "lat": 27.3, "lng": 170.0, "PRES": 960.0, "WND": 40.0}, {"time": "1993-08-22 18:00:00", "power": 4, "lat": 27.8, "lng": 169.4, "PRES": 965.0, "WND": 40.0}, {"time": "1993-08-23 00:00:00", "power": 4, "lat": 28.2, "lng": 168.6, "PRES": 970.0, "WND": 35.0}, {"time": "1993-08-23 06:00:00", "power": 4, "lat": 28.6, "lng": 167.5, "PRES": 970.0, "WND": 35.0}, {"time": "1993-08-23 12:00:00", "power": 3, "lat": 28.8, "lng": 166.2, "PRES": 975.0, "WND": 30.0}, {"time": "1993-08-23 18:00:00", "power": 3, "lat": 29.0, "lng": 164.8, "PRES": 975.0, "WND": 30.0}, {"time": "1993-08-24 00:00:00", "power": 3, "lat": 29.4, "lng": 163.5, "PRES": 980.0, "WND": 30.0}, {"time": "1993-08-24 06:00:00", "power": 3, "lat": 30.1, "lng": 162.5, "PRES": 980.0, "WND": 30.0}, {"time": "1993-08-24 12:00:00", "power": 3, "lat": 30.9, "lng": 161.9, "PRES": 975.0, "WND": 30.0}, {"time": "1993-08-24 18:00:00", "power": 4, "lat": 31.6, "lng": 161.2, "PRES": 970.0, "WND": 35.0}, {"time": "1993-08-25 00:00:00", "power": 4, "lat": 32.1, "lng": 160.5, "PRES": 970.0, "WND": 35.0}, {"time": "1993-08-25 06:00:00", "power": 4, "lat": 32.3, "lng": 159.9, "PRES": 970.0, "WND": 35.0}, {"time": "1993-08-25 12:00:00", "power": 4, "lat": 32.4, "lng": 159.6, "PRES": 970.0, "WND": 35.0}, {"time": "1993-08-25 18:00:00", "power": 3, "lat": 32.5, "lng": 159.4, "PRES": 975.0, "WND": 30.0}, {"time": "1993-08-26 00:00:00", "power": 3, "lat": 32.6, "lng": 159.2, "PRES": 975.0, "WND": 30.0}, {"time": "1993-08-26 06:00:00", "power": 3, "lat": 33.1, "lng": 158.7, "PRES": 980.0, "WND": 30.0}, {"time": "1993-08-26 12:00:00", "power": 3, "lat": 33.8, "lng": 158.5, "PRES": 985.0, "WND": 25.0}, {"time": "1993-08-26 18:00:00", "power": 3, "lat": 34.6, "lng": 158.4, "PRES": 985.0, "WND": 25.0}, {"time": "1993-08-27 00:00:00", "power": 3, "lat": 35.5, "lng": 158.5, "PRES": 985.0, "WND": 25.0}, {"time": "1993-08-27 06:00:00", "power": 2, "lat": 36.1, "lng": 158.6, "PRES": 990.0, "WND": 20.0}, {"time": "1993-08-27 12:00:00", "power": 2, "lat": 36.7, "lng": 158.7, "PRES": 990.0, "WND": 20.0}, {"time": "1993-08-27 18:00:00", "power": 2, "lat": 37.1, "lng": 159.2, "PRES": 990.0, "WND": 20.0}, {"time": "1993-08-28 00:00:00", "power": 2, "lat": 37.3, "lng": 160.1, "PRES": 995.0, "WND": 20.0}, {"time": "1993-08-28 06:00:00", "power": 1, "lat": 37.0, "lng": 161.5, "PRES": 1000.0, "WND": 15.0}, {"time": "1993-08-28 12:00:00", "power": 1, "lat": 36.5, "lng": 162.5, "PRES": 1000.0, "WND": 15.0}, {"time": "1993-08-28 18:00:00", "power": 1, "lat": 35.7, "lng": 163.6, "PRES": 1005.0, "WND": 12.0}, {"time": "1993-08-29 00:00:00", "power": 1, "lat": 35.0, "lng": 165.0, "PRES": 1005.0, "WND": 12.0}, {"time": "1993-08-29 06:00:00", "power": 0, "lat": 34.5, "lng": 166.0, "PRES": 1010.0, "WND": 10.0}, {"time": "1993-08-29 12:00:00", "power": 0, "lat": 33.6, "lng": 166.7, "PRES": 1010.0, "WND": 10.0}, {"time": "1993-08-29 18:00:00", "power": 0, "lat": 32.7, "lng": 167.0, "PRES": 1010.0, "WND": 10.0}, {"time": "1993-08-30 00:00:00", "power": 0, "lat": 31.5, "lng": 167.0, "PRES": 1010.0, "WND": 10.0}, {"time": "1993-08-30 06:00:00", "power": 0, "lat": 30.5, "lng": 167.0, "PRES": 1010.0, "WND": 10.0}]}